{
  "copyright": "Copyright 2026 MLB Advanced Media, L.P.  Use of any content on this page acknowledges agreement to the terms posted here http://gdx.mlb.com/components/copyright.txt",
  "stats": [
    {
      "type": {
        "displayName": "season"
      },
      "group": {
        "displayName": "hitting"
      },
      "exemptions": [],
      "splits": [
        {
          "season": "2025",
          "stat": {
            "age": 35,
            "gamesPlayed": 140,
            "groundOuts": 105,
            "airOuts": 132,
            "runs": 106,
            "doubles": 27,
            "triples": 1,
            "homeRuns": 32,
            "strikeOuts": 111,
            "baseOnBalls": 69,
            "intentionalWalks": 3,
            "hits": 154,
            "hitByPitch": 8,
            "avg": ".309",
            "atBats": 498,
            "obp": ".399",
            "slg": ".560",
            "ops": ".959",
            "caughtStealing": 1,
            "stolenBases": 18,
            "stolenBasePercentage": ".947",
            "caughtStealingPercentage": ".053",
            "groundIntoDoublePlay": 14,
            "numberOfPitches": 2307,
            "plateAppearances": 586,
            "totalBases": 279,
            "rbi": 84,
            "leftOnBase": 183,
            "sacBunts": 0,
            "sacFlies": 4,
            "babip": ".340",
            "groundOutsToAirouts": "0.80",
            "catchersInterference": 7,
            "atBatsPerHomeRun": "15.56"
          },
          "team": {
            "id": 141,
            "name": "Toronto Blue Jays",
            "link": "/api/v1/teams/141"
          },
          "player": {
            "id": 543807,
            "fullName": "George Springer",
            "link": "/api/v1/people/543807"
          },
          "league": {
            "id": 103,
            "name": "American League",
            "link": "/api/v1/league/103"
          },
          "sport": {
            "id": 1,
            "link": "/api/v1/sports/1",
            "abbreviation": "MLB"
          },
          "gameType": "R"
        }
      ]
    }
  ]
}