{
  "copyright": "Copyright 2026 MLB Advanced Media, L.P.  Use of any content on this page acknowledges agreement to the terms posted here http://gdx.mlb.com/components/copyright.txt",
  "stats": [
    {
      "type": {
        "displayName": "season"
      },
      "group": {
        "displayName": "hitting"
      },
      "exemptions": [],
      "splits": [
        {
          "season": "2026",
          "stat": {
            "age": 29,
            "gamesPlayed": 5,
            "groundOuts": 6,
            "airOuts": 8,
            "runs": 2,
            "doubles": 0,
            "triples": 0,
            "homeRuns": 1,
            "strikeOuts": 1,
            "baseOnBalls": 3,
            "intentionalWalks": 0,
            "hits": 2,
            "hitByPitch": 1,
            "avg": ".118",
            "atBats": 17,
            "obp": ".286",
            "slg": ".294",
            "ops": ".580",
            "caughtStealing": 0,
            "stolenBases": 0,
            "stolenBasePercentage": ".---",
            "caughtStealingPercentage": ".---",
            "groundIntoDoublePlay": 1,
            "numberOfPitches": 80,
            "plateAppearances": 21,
            "totalBases": 5,
            "rbi": 4,
            "leftOnBase": 7,
            "sacBunts": 0,
            "sacFlies": 0,
            "babip": ".067",
            "groundOutsToAirouts": "0.75",
            "catchersInterference": 0,
            "atBatsPerHomeRun": "17.00"
          },
          "team": {
            "id": 143,
            "name": "Philadelphia Phillies",
            "link": "/api/v1/teams/143"
          },
          "player": {
            "id": 664761,
            "fullName": "Alec Bohm",
            "link": "/api/v1/people/664761"
          },
          "league": {
            "id": 104,
            "name": "National League",
            "link": "/api/v1/league/104"
          },
          "sport": {
            "id": 1,
            "link": "/api/v1/sports/1",
            "abbreviation": "MLB"
          },
          "gameType": "R"
        }
      ]
    }
  ]
}